HBT_IP_Test/__init__.py
HBT_IP_Test/hbt_core.py
HBT_IP_Test/hbt_spg.py
HBT_IP_Test/libs/Cameras_pb2.py
HBT_IP_Test/libs/CodecDetails_pb2.py
HBT_IP_Test/libs/IsomDeviceMgmt_pb2.py
HBT_IP_Test/libs/IsomDevices_pb2.py
HBT_IP_Test/libs/IsomStdDef_pb2.py
HBT_IP_Test/libs/Isom_pb2.py
HBT_IP_Test/libs/__init__.py
HBT_IP_Test/libs/hbt_pb2.py
HBT_IP_Test/libs/sparkplug_b.py
HBT_IP_Test/libs/sparkplug_b_pb2.py
HBT_IP_Test/libs/hbt/__init__.py
HBT_IP_Test/libs/hbt/hbt_pb2.py
HBT_IP_Test/libs/isom/__init__.py
HBT_IP_Test/libs/isom/python/AC_pb2.py
HBT_IP_Test/libs/isom/python/ActivationGroupTypes_pb2.py
HBT_IP_Test/libs/isom/python/ActivationGroups_pb2.py
HBT_IP_Test/libs/isom/python/Analytics_e_pb2.py
HBT_IP_Test/libs/isom/python/Analytics_pb2.py
HBT_IP_Test/libs/isom/python/AudioSources_pb2.py
HBT_IP_Test/libs/isom/python/BatteryPeripheral_pb2.py
HBT_IP_Test/libs/isom/python/COSensor_pb2.py
HBT_IP_Test/libs/isom/python/Cameras_e_pb2.py
HBT_IP_Test/libs/isom/python/Cameras_pb2.py
HBT_IP_Test/libs/isom/python/CellularInterfaces_e_pb2.py
HBT_IP_Test/libs/isom/python/CellularInterfaces_pb2.py
HBT_IP_Test/libs/isom/python/Channels_pb2.py
HBT_IP_Test/libs/isom/python/Clips_e_pb2.py
HBT_IP_Test/libs/isom/python/Clips_pb2.py
HBT_IP_Test/libs/isom/python/CodecDetails_pb2.py
HBT_IP_Test/libs/isom/python/DetectorGroupTypes_pb2.py
HBT_IP_Test/libs/isom/python/DetectorGroups_e_pb2.py
HBT_IP_Test/libs/isom/python/DetectorGroups_pb2.py
HBT_IP_Test/libs/isom/python/Files_e_pb2.py
HBT_IP_Test/libs/isom/python/Files_pb2.py
HBT_IP_Test/libs/isom/python/Flashers_pb2.py
HBT_IP_Test/libs/isom/python/GBSensors_pb2.py
HBT_IP_Test/libs/isom/python/IsomAccessPoints_e_pb2.py
HBT_IP_Test/libs/isom/python/IsomAccessPoints_pb2.py
HBT_IP_Test/libs/isom/python/IsomAccounts_e_pb2.py
HBT_IP_Test/libs/isom/python/IsomAccounts_pb2.py
HBT_IP_Test/libs/isom/python/IsomAssets_e_pb2.py
HBT_IP_Test/libs/isom/python/IsomAssets_pb2.py
HBT_IP_Test/libs/isom/python/IsomBinaryHeader_pb2.py
HBT_IP_Test-1.0.1.dist-info/LICENSE
HBT_IP_Test-1.0.1.dist-info/METADATA
HBT_IP_Test-1.0.1.dist-info/WHEEL
HBT_IP_Test-1.0.1.dist-info/top_level.txt
HBT_IP_Test-1.0.1.dist-info/RECORD
